ai/__init__.py
ai/ai.py
ai/cli.py
ai/crud.py
ai/database.py
ai/tui.py
ai/css/style.css
aitui-0.0.2.dist-info/METADATA
aitui-0.0.2.dist-info/WHEEL
aitui-0.0.2.dist-info/entry_points.txt
aitui-0.0.2.dist-info/top_level.txt
aitui-0.0.2.dist-info/RECORD
