Metadata-Version: 2.1
Name: aitui
Version: 0.0.2
Home-page: 
Author: Ben Hammel
Author-email: bdhammel@gmail.com
License: MIT
Requires-Dist: openai
Requires-Dist: textual (>=0.15)
Requires-Dist: pydantic
